{"metadata": {"version": 1.0}, "entries": [{"creationDate": "2020-06-20T02:31:45Z", "tags": ["typographical"]}, {"creationDate": "2020-06-19T20:27:36Z", "tags": ["tankards"]}, {"creationDate": "2020-06-19T15:06:52Z", "tags": ["spencer"]}, {"creationDate": "2020-06-19T09:06:39Z", "tags": ["vituperously"]}, {"creationDate": "2020-06-19T02:53:50Z", "tags": ["typographical"]}, {"creationDate": "2020-06-18T17:03:08Z", "tags": ["Wikisource"]}, {"creationDate": "2020-06-18T07:44:00Z", "tags": ["tankards"]}, {"creationDate": "2020-06-18T00:13:38Z", "tags": ["tankards"]}, {"creationDate": "2020-06-16T18:26:17Z", "tags": ["pelow"]}, {"creationDate": "2020-06-16T13:12:58Z", "tags": ["sonication"]}, {"creationDate": "2020-06-16T03:12:57Z", "tags": ["hobbyhorse"]}, {"creationDate": "2020-06-15T18:40:03Z", "tags": ["vituperously"]}, {"creationDate": "2020-06-15T12:00:03Z", "tags": ["hobbyhorse"]}, {"creationDate": "2020-06-15T01:55:16Z", "tags": ["pelow"]}, {"creationDate": "2020-06-13T17:33:36Z", "tags": ["hobbyhorse"]}, {"creationDate": "2020-06-13T07:15:35Z", "tags": ["sonication"]}, {"creationDate": "2020-06-13T00:36:20Z", "tags": ["castigating"]}, {"creationDate": "2020-06-12T19:11:50Z", "tags": ["hobbyhorse"]}, {"creationDate": "2020-06-12T10:09:41Z", "tags": ["castigating"]}, {"creationDate": "2020-06-11T03:52:43Z", "tags": ["vituperously"]}, {"creationDate": "2020-06-10T20:05:36Z", "tags": ["castigating"]}, {"creationDate": "2020-06-10T10:59:02Z", "tags": ["castigating"]}, {"creationDate": "2020-06-10T04:29:34Z", "tags": ["hobbyhorse"]}, {"creationDate": "2020-06-09T19:29:49Z", "tags": ["Wikisource"]}, {"creationDate": "2020-06-09T08:35:18Z", "tags": ["Wikisource"]}, {"creationDate": "2020-06-07T23:14:18Z", "tags": ["hobbyhorse"]}, {"creationDate": "2020-06-07T15:53:43Z", "tags": ["castigating"]}, {"creationDate": "2020-06-07T04:55:40Z", "tags": ["shaka"]}, {"creationDate": "2020-06-06T22:07:40Z", "tags": ["castigating"]}, {"creationDate": "2020-06-06T16:30:10Z", "tags": ["hobbyhorse"]}, {"creationDate": "2020-06-06T11:08:53Z", "tags": ["pelow"]}, {"creationDate": "2020-06-06T05:01:03Z", "tags": ["typographical"]}, {"creationDate": "2020-06-05T19:41:32Z", "tags": ["typographical"]}, {"creationDate": "2020-06-05T09:00:55Z", "tags": ["sonication"]}, {"creationDate": "2020-06-05T00:40:25Z", "tags": ["shaka"]}, {"creationDate": "2020-06-03T18:19:00Z", "tags": ["Wikisource"]}, {"creationDate": "2020-06-03T07:39:16Z", "tags": ["hobbyhorse"]}, {"creationDate": "2020-06-02T20:42:00Z", "tags": ["typographical"]}, {"creationDate": "2020-06-02T15:34:02Z", "tags": ["typographical"]}, {"creationDate": "2020-06-02T06:24:02Z", "tags": ["vituperously"]}, {"creationDate": "2020-05-31T23:11:13Z", "tags": ["spencer"]}, {"creationDate": "2020-05-31T13:09:28Z", "tags": ["castigating"]}, {"creationDate": "2020-05-31T06:26:19Z", "tags": ["spencer"]}, {"creationDate": "2020-05-31T01:08:09Z", "tags": ["tankards"]}, {"creationDate": "2020-05-30T19:41:50Z", "tags": ["typographical"]}, {"creationDate": "2020-05-30T09:49:53Z", "tags": ["tankards"]}, {"creationDate": "2020-05-30T02:52:35Z", "tags": ["shaka"]}, {"creationDate": "2020-05-29T16:09:10Z", "tags": ["pelow"]}, {"creationDate": "2020-05-28T08:35:39Z", "tags": ["spencer"]}, {"creationDate": "2020-05-27T23:23:07Z", "tags": ["hobbyhorse"]}, {"creationDate": "2020-05-27T18:08:44Z", "tags": ["shaka"]}, {"creationDate": "2020-05-27T11:37:06Z", "tags": ["tankards"]}, {"creationDate": "2020-05-27T01:51:47Z", "tags": ["hobbyhorse"]}, {"creationDate": "2020-05-26T15:21:31Z", "tags": ["castigating"]}, {"creationDate": "2020-05-26T09:45:07Z", "tags": ["spencer"]}, {"creationDate": "2020-05-24T22:45:07Z", "tags": ["Wikisource"]}, {"creationDate": "2020-05-24T15:51:40Z", "tags": ["Wikisource"]}, {"creationDate": "2020-05-24T07:08:15Z", "tags": ["tankards"]}, {"creationDate": "2020-05-23T20:41:47Z", "tags": ["castigating"]}, {"creationDate": "2020-05-23T11:03:33Z", "tags": ["pelow"]}, {"creationDate": "2020-05-22T05:18:10Z", "tags": ["hobbyhorse"]}, {"creationDate": "2020-05-21T18:24:11Z", "tags": ["pelow"]}, {"creationDate": "2020-05-21T10:38:38Z", "tags": ["typographical"]}, {"creationDate": "2020-05-21T00:38:41Z", "tags": ["castigating"]}, {"creationDate": "2020-05-20T18:47:39Z", "tags": ["vituperously"]}, {"creationDate": "2020-05-20T12:50:35Z", "tags": ["tankards"]}, {"creationDate": "2020-05-20T04:02:15Z", "tags": ["castigating"]}, {"creationDate": "2020-05-19T22:28:13Z", "tags": ["Wikisource"]}, {"creationDate": "2020-05-19T14:13:31Z", "tags": ["sonication"]}, {"creationDate": "2020-05-19T07:26:30Z", "tags": ["Wikisource"]}, {"creationDate": "2020-05-18T02:23:27Z", "tags": ["shaka"]}, {"creationDate": "2020-05-17T16:40:14Z", "tags": ["pelow"]}, {"creationDate": "2020-05-17T06:35:52Z", "tags": ["typographical"]}, {"creationDate": "2020-05-16T22:36:58Z", "tags": ["spencer"]}, {"creationDate": "2020-05-16T16:41:38Z", "tags": ["sonication"]}, {"creationDate": "2020-05-15T07:49:36Z", "tags": ["Wikisource"]}, {"creationDate": "2020-05-14T21:57:58Z", "tags": ["typographical"]}, {"creationDate": "2020-05-14T13:19:03Z", "tags": ["Wikisource"]}, {"creationDate": "2020-05-14T03:09:31Z", "tags": ["shaka"]}, {"creationDate": "2020-05-13T17:00:23Z", "tags": ["sonication"]}, {"creationDate": "2020-05-13T10:24:02Z", "tags": ["hobbyhorse"]}, {"creationDate": "2020-05-13T03:22:16Z", "tags": ["spencer"]}, {"creationDate": "2020-05-12T20:29:18Z", "tags": ["spencer"]}, {"creationDate": "2020-05-12T15:20:42Z", "tags": ["tankards"]}, {"creationDate": "2020-05-12T09:43:02Z", "tags": ["shaka"]}, {"creationDate": "2020-05-11T04:33:30Z", "tags": ["pelow"]}, {"creationDate": "2020-05-10T20:53:14Z", "tags": ["hobbyhorse"]}, {"creationDate": "2020-05-10T11:16:14Z", "tags": ["sonication"]}, {"creationDate": "2020-05-10T05:22:48Z", "tags": ["shaka"]}, {"creationDate": "2020-05-09T20:55:03Z", "tags": ["pelow"]}, {"creationDate": "2020-05-09T10:13:32Z", "tags": ["pelow"]}, {"creationDate": "2020-05-09T01:04:38Z", "tags": ["vituperously"]}, {"creationDate": "2020-05-08T16:10:39Z", "tags": ["spencer"]}, {"creationDate": "2020-05-07T05:29:59Z", "tags": ["pelow"]}, {"creationDate": "2020-05-06T22:40:29Z", "tags": ["hobbyhorse"]}, {"creationDate": "2020-05-06T16:10:35Z", "tags": ["pelow"]}, {"creationDate": "2020-05-06T07:32:25Z", "tags": ["spencer"]}, {"creationDate": "2020-05-05T23:09:30Z", "tags": ["shaka"]}, {"creationDate": "2020-05-05T12:47:03Z", "tags": ["shaka"]}, {"creationDate": "2020-05-05T02:59:11Z", "tags": ["tankards"]}, {"creationDate": "2020-05-03T19:05:42Z", "tags": ["shaka"]}, {"creationDate": "2020-05-03T13:38:16Z", "tags": ["castigating"]}, {"creationDate": "2020-05-03T03:25:11Z", "tags": ["sonication"]}, {"creationDate": "2020-05-02T17:50:34Z", "tags": ["pelow"]}, {"creationDate": "2020-05-02T08:47:05Z", "tags": ["castigating"]}, {"creationDate": "2020-05-01T22:53:32Z", "tags": ["hobbyhorse"]}, {"creationDate": "2020-05-01T13:37:46Z", "tags": ["sonication"]}, {"creationDate": "2020-04-30T03:20:07Z", "tags": ["spencer"]}, {"creationDate": "2020-04-29T19:45:05Z", "tags": ["shaka"]}, {"creationDate": "2020-04-29T13:44:43Z", "tags": ["pelow"]}, {"creationDate": "2020-04-29T07:58:55Z", "tags": ["vituperously"]}, {"creationDate": "2020-04-28T23:03:52Z", "tags": ["hobbyhorse"]}, {"creationDate": "2020-04-28T17:51:15Z", "tags": ["spencer"]}, {"creationDate": "2020-04-27T12:11:53Z", "tags": ["hobbyhorse"]}, {"creationDate": "2020-04-27T02:03:21Z", "tags": ["spencer"]}, {"creationDate": "2020-04-26T20:33:12Z", "tags": ["spencer"]}, {"creationDate": "2020-04-26T10:52:09Z", "tags": ["hobbyhorse"]}, {"creationDate": "2020-04-26T00:48:13Z", "tags": ["castigating"]}, {"creationDate": "2020-04-25T14:27:03Z", "tags": ["shaka"]}, {"creationDate": "2020-04-25T04:01:19Z", "tags": ["typographical"]}, {"creationDate": "2020-04-23T17:50:11Z", "tags": ["Wikisource"]}, {"creationDate": "2020-04-23T08:31:10Z", "tags": ["spencer"]}, {"creationDate": "2020-04-22T21:43:36Z", "tags": ["castigating"]}, {"creationDate": "2020-04-22T14:25:15Z", "tags": ["spencer"]}, {"creationDate": "2020-04-22T03:48:45Z", "tags": ["vituperously"]}, {"creationDate": "2020-04-20T21:07:40Z", "tags": ["tankards"]}, {"creationDate": "2020-04-20T15:29:20Z", "tags": ["vituperously"]}, {"creationDate": "2020-04-20T07:04:21Z", "tags": ["tankards"]}, {"creationDate": "2020-04-20T00:25:25Z", "tags": ["vituperously"]}, {"creationDate": "2020-04-19T18:49:53Z", "tags": ["vituperously"]}, {"creationDate": "2020-04-19T12:24:08Z", "tags": ["vituperously"]}, {"creationDate": "2020-04-19T03:24:04Z", "tags": ["tankards"]}, {"creationDate": "2020-04-18T21:35:34Z", "tags": ["shaka"]}, {"creationDate": "2020-04-17T10:48:12Z", "tags": ["tankards"]}, {"creationDate": "2020-04-17T00:24:49Z", "tags": ["tankards"]}, {"creationDate": "2020-04-16T14:08:41Z", "tags": ["shaka"]}, {"creationDate": "2020-04-16T04:41:42Z", "tags": ["Wikisource"]}, {"creationDate": "2020-04-15T19:03:31Z", "tags": ["Wikisource"]}, {"creationDate": "2020-04-15T08:15:34Z", "tags": ["Wikisource"]}, {"creationDate": "2020-04-15T02:17:24Z", "tags": ["sonication"]}, {"creationDate": "2020-04-14T20:56:06Z", "tags": ["sonication"]}, {"creationDate": "2020-04-14T12:20:37Z", "tags": ["castigating"]}, {"creationDate": "2020-04-14T06:54:17Z", "tags": ["typographical"]}, {"creationDate": "2020-04-12T20:09:30Z", "tags": ["spencer"]}, {"creationDate": "2020-04-12T11:04:41Z", "tags": ["Wikisource"]}, {"creationDate": "2020-04-12T02:58:50Z", "tags": ["Wikisource"]}, {"creationDate": "2020-04-11T20:03:20Z", "tags": ["vituperously"]}, {"creationDate": "2020-04-11T09:44:18Z", "tags": ["tankards"]}, {"creationDate": "2020-04-11T04:03:41Z", "tags": ["shaka"]}, {"creationDate": "2020-04-10T20:53:41Z", "tags": ["shaka"]}, {"creationDate": "2020-04-09T14:17:06Z", "tags": ["tankards"]}, {"creationDate": "2020-04-09T08:29:18Z", "tags": ["castigating"]}, {"creationDate": "2020-04-08T23:33:21Z", "tags": ["typographical"]}, {"creationDate": "2020-04-08T16:55:26Z", "tags": ["tankards"]}, {"creationDate": "2020-04-08T06:02:42Z", "tags": ["pelow"]}, {"creationDate": "2020-04-07T20:39:55Z", "tags": ["Wikisource"]}, {"creationDate": "2020-04-07T12:18:39Z", "tags": ["castigating"]}, {"creationDate": "2020-04-06T04:01:28Z", "tags": ["pelow"]}, {"creationDate": "2020-04-05T21:49:00Z", "tags": ["Wikisource"]}, {"creationDate": "2020-04-05T12:58:35Z", "tags": ["hobbyhorse"]}, {"creationDate": "2020-04-05T03:08:47Z", "tags": ["pelow"]}, {"creationDate": "2020-04-04T18:53:54Z", "tags": ["tankards"]}, {"creationDate": "2020-04-04T13:18:37Z", "tags": ["tankards"]}, {"creationDate": "2020-04-04T04:47:26Z", "tags": ["sonication"]}, {"creationDate": "2020-04-02T23:31:16Z", "tags": ["Wikisource"]}, {"creationDate": "2020-04-02T12:52:26Z", "tags": ["tankards"]}, {"creationDate": "2020-04-02T06:33:51Z", "tags": ["shaka"]}, {"creationDate": "2020-04-01T20:53:36Z", "tags": ["hobbyhorse"]}, {"creationDate": "2020-04-01T15:19:12Z", "tags": ["Wikisource"]}, {"creationDate": "2020-04-01T08:45:56Z", "tags": ["spencer"]}, {"creationDate": "2020-04-01T00:05:26Z", "tags": ["tankards"]}, {"creationDate": "2020-03-31T17:15:44Z", "tags": ["Wikisource"]}, {"creationDate": "2020-03-31T08:36:03Z", "tags": ["tankards"]}, {"creationDate": "2020-03-30T23:43:47Z", "tags": ["sonication"]}, {"creationDate": "2020-03-29T15:09:19Z", "tags": ["vituperously"]}, {"creationDate": "2020-03-29T04:51:18Z", "tags": ["castigating"]}, {"creationDate": "2020-03-28T19:52:11Z", "tags": ["pelow"]}, {"creationDate": "2020-03-28T12:30:07Z", "tags": ["sonication"]}, {"creationDate": "2020-03-28T03:06:54Z", "tags": ["typographical"]}, {"creationDate": "2020-03-27T20:26:06Z", "tags": ["sonication"]}, {"creationDate": "2020-03-27T11:34:39Z", "tags": ["vituperously"]}, {"creationDate": "2020-03-27T01:18:26Z", "tags": ["typographical"]}, {"creationDate": "2020-03-26T15:30:46Z", "tags": ["Wikisource"]}, {"creationDate": "2020-03-26T08:47:43Z", "tags": ["Wikisource"]}, {"creationDate": "2020-03-24T23:21:00Z", "tags": ["Wikisource"]}, {"creationDate": "2020-03-24T16:59:09Z", "tags": ["tankards"]}, {"creationDate": "2020-03-24T06:23:34Z", "tags": ["typographical"]}, {"creationDate": "2020-03-23T21:13:46Z", "tags": ["tankards"]}, {"creationDate": "2020-03-23T15:33:31Z", "tags": ["shaka"]}, {"creationDate": "2020-03-23T05:43:22Z", "tags": ["spencer"]}, {"creationDate": "2020-03-22T20:56:12Z", "tags": ["pelow"]}, {"creationDate": "2020-03-22T12:15:53Z", "tags": ["tankards"]}, {"creationDate": "2020-03-21T06:20:21Z", "tags": ["pelow"]}, {"creationDate": "2020-03-20T22:29:00Z", "tags": ["vituperously"]}, {"creationDate": "2020-03-20T16:34:20Z", "tags": ["castigating"]}, {"creationDate": "2020-03-20T07:48:56Z", "tags": ["tankards"]}, {"creationDate": "2020-03-19T22:36:43Z", "tags": ["hobbyhorse"]}, {"creationDate": "2020-03-19T13:05:23Z", "tags": ["Wikisource"]}, {"creationDate": "2020-03-19T07:20:32Z", "tags": ["tankards"]}, {"creationDate": "2020-03-19T01:24:42Z", "tags": ["typographical"]}, {"creationDate": "2020-03-18T19:45:29Z", "tags": ["sonication"]}, {"creationDate": "2020-03-17T13:36:31Z", "tags": ["spencer"]}, {"creationDate": "2020-03-17T04:31:03Z", "tags": ["spencer"]}, {"creationDate": "2020-03-16T21:47:31Z", "tags": ["castigating"]}, {"creationDate": "2020-03-16T11:36:46Z", "tags": ["typographical"]}, {"creationDate": "2020-03-16T01:36:31Z", "tags": ["typographical"]}, {"creationDate": "2020-03-15T19:38:33Z", "tags": ["vituperously"]}, {"creationDate": "2020-03-15T08:51:26Z", "tags": ["tankards"]}, {"creationDate": "2020-03-14T23:55:59Z", "tags": ["tankards"]}, {"creationDate": "2020-03-14T14:34:05Z", "tags": ["sonication"]}, {"creationDate": "2020-03-14T05:40:31Z", "tags": ["castigating"]}, {"creationDate": "2020-03-12T21:00:41Z", "tags": ["sonication"]}, {"creationDate": "2020-03-12T14:55:23Z", "tags": ["vituperously"]}, {"creationDate": "2020-03-12T07:23:45Z", "tags": ["sonication"]}, {"creationDate": "2020-03-11T22:44:55Z", "tags": ["spencer"]}, {"creationDate": "2020-03-11T13:17:51Z", "tags": ["shaka"]}, {"creationDate": "2020-03-11T02:51:13Z", "tags": ["sonication"]}, {"creationDate": "2020-03-10T16:34:07Z", "tags": ["castigating"]}, {"creationDate": "2020-03-10T05:55:26Z", "tags": ["hobbyhorse"]}, {"creationDate": "2020-03-10T00:35:30Z", "tags": ["shaka"]}, {"creationDate": "2020-03-08T15:30:51Z", "tags": ["spencer"]}, {"creationDate": "2020-03-08T09:21:06Z", "tags": ["castigating"]}, {"creationDate": "2020-03-08T03:47:54Z", "tags": ["tankards"]}, {"creationDate": "2020-03-07T18:30:54Z", "tags": ["spencer"]}, {"creationDate": "2020-03-07T08:40:27Z", "tags": ["tankards"]}, {"creationDate": "2020-03-07T00:28:55Z", "tags": ["typographical"]}, {"creationDate": "2020-03-06T14:42:58Z", "tags": ["hobbyhorse"]}, {"creationDate": "2020-03-05T08:02:14Z", "tags": ["castigating"]}, {"creationDate": "2020-03-04T23:14:57Z", "tags": ["spencer"]}, {"creationDate": "2020-03-04T17:50:30Z", "tags": ["vituperously"]}, {"creationDate": "2020-03-04T10:41:01Z", "tags": ["Wikisource"]}, {"creationDate": "2020-03-04T01:03:45Z", "tags": ["shaka"]}, {"creationDate": "2020-03-02T16:21:16Z", "tags": ["tankards"]}, {"creationDate": "2020-03-02T06:29:28Z", "tags": ["sonication"]}, {"creationDate": "2020-03-02T00:09:08Z", "tags": ["spencer"]}, {"creationDate": "2020-03-01T14:42:44Z", "tags": ["shaka"]}, {"creationDate": "2020-03-01T08:50:46Z", "tags": ["vituperously"]}, {"creationDate": "2020-03-01T03:31:36Z", "tags": ["pelow"]}, {"creationDate": "2020-02-29T20:04:47Z", "tags": ["vituperously"]}, {"creationDate": "2020-02-28T14:51:05Z", "tags": ["sonication"]}, {"creationDate": "2020-02-28T07:22:42Z", "tags": ["pelow"]}, {"creationDate": "2020-02-28T02:12:05Z", "tags": ["sonication"]}, {"creationDate": "2020-02-27T17:56:42Z", "tags": ["castigating"]}, {"creationDate": "2020-02-27T07:02:30Z", "tags": ["tankards"]}, {"creationDate": "2020-02-27T01:58:04Z", "tags": ["spencer"]}, {"creationDate": "2020-02-26T17:38:19Z", "tags": ["spencer"]}, {"creationDate": "2020-02-26T06:37:57Z", "tags": ["tankards"]}, {"creationDate": "2020-02-26T01:07:31Z", "tags": ["vituperously"]}, {"creationDate": "2020-02-25T16:50:21Z", "tags": ["tankards"]}, {"creationDate": "2020-02-24T11:36:00Z", "tags": ["shaka"]}, {"creationDate": "2020-02-24T01:35:47Z", "tags": ["pelow"]}, {"creationDate": "2020-02-23T14:37:56Z", "tags": ["shaka"]}, {"creationDate": "2020-02-23T06:28:26Z", "tags": ["tankards"]}, {"creationDate": "2020-02-22T22:10:03Z", "tags": ["hobbyhorse"]}, {"creationDate": "2020-02-22T16:01:55Z", "tags": ["castigating"]}, {"creationDate": "2020-02-21T10:02:32Z", "tags": ["shaka"]}, {"creationDate": "2020-02-21T00:22:24Z", "tags": ["shaka"]}, {"creationDate": "2020-02-20T19:03:52Z", "tags": ["typographical"]}, {"creationDate": "2020-02-20T08:12:39Z", "tags": ["Wikisource"]}, {"creationDate": "2020-02-19T23:48:51Z", "tags": ["shaka"]}, {"creationDate": "2020-02-19T14:47:57Z", "tags": ["shaka"]}, {"creationDate": "2020-02-19T09:06:01Z", "tags": ["typographical"]}, {"creationDate": "2020-02-19T01:12:55Z", "tags": ["hobbyhorse"]}, {"creationDate": "2020-02-18T15:06:33Z", "tags": ["typographical"]}, {"creationDate": "2020-02-18T08:08:37Z", "tags": ["shaka"]}, {"creationDate": "2020-02-17T00:38:37Z", "tags": ["pelow"]}, {"creationDate": "2020-02-16T15:50:08Z", "tags": ["shaka"]}, {"creationDate": "2020-02-16T09:12:15Z", "tags": ["vituperously"]}, {"creationDate": "2020-02-15T22:44:05Z", "tags": ["shaka"]}, {"creationDate": "2020-02-15T12:24:52Z", "tags": ["spencer"]}, {"creationDate": "2020-02-15T05:54:40Z", "tags": ["hobbyhorse"]}, {"creationDate": "2020-02-14T20:55:44Z", "tags": ["typographical"]}, {"creationDate": "2020-02-14T12:08:57Z", "tags": ["pelow"]}, {"creationDate": "2020-02-14T07:00:18Z", "tags": ["shaka"]}, {"creationDate": "2020-02-12T21:03:14Z", "tags": ["castigating"]}, {"creationDate": "2020-02-12T13:49:48Z", "tags": ["tankards"]}, {"creationDate": "2020-02-12T06:29:52Z", "tags": ["Wikisource"]}, {"creationDate": "2020-02-11T22:42:27Z", "tags": ["vituperously"]}, {"creationDate": "2020-02-11T14:50:43Z", "tags": ["pelow"]}, {"creationDate": "2020-02-11T04:44:46Z", "tags": ["hobbyhorse"]}, {"creationDate": "2020-02-10T20:52:24Z", "tags": ["hobbyhorse"]}, {"creationDate": "2020-02-10T15:46:59Z", "tags": ["tankards"]}, {"creationDate": "2020-02-09T07:40:38Z", "tags": ["tankards"]}, {"creationDate": "2020-02-08T22:17:33Z", "tags": ["vituperously"]}, {"creationDate": "2020-02-08T16:25:04Z", "tags": ["hobbyhorse"]}, {"creationDate": "2020-02-08T06:04:13Z", "tags": ["castigating"]}, {"creationDate": "2020-02-07T20:57:10Z", "tags": ["pelow"]}, {"creationDate": "2020-02-06T13:06:15Z", "tags": ["tankards"]}, {"creationDate": "2020-02-06T05:35:33Z", "tags": ["pelow"]}, {"creationDate": "2020-02-05T19:59:41Z", "tags": ["castigating"]}, {"creationDate": "2020-02-05T12:47:46Z", "tags": ["pelow"]}, {"creationDate": "2020-02-05T05:55:46Z", "tags": ["hobbyhorse"]}, {"creationDate": "2020-02-03T20:58:35Z", "tags": ["shaka"]}, {"creationDate": "2020-02-03T13:59:45Z", "tags": ["hobbyhorse"]}, {"creationDate": "2020-02-03T07:57:27Z", "tags": ["tankards"]}, {"creationDate": "2020-02-03T01:59:45Z", "tags": ["shaka"]}, {"creationDate": "2020-02-02T20:04:45Z", "tags": ["shaka"]}, {"creationDate": "2020-02-02T12:08:29Z", "tags": ["pelow"]}, {"creationDate": "2020-02-02T03:08:04Z", "tags": ["spencer"]}, {"creationDate": "2020-01-31T16:22:17Z", "tags": ["vituperously"]}, {"creationDate": "2020-01-31T06:02:09Z", "tags": ["spencer"]}, {"creationDate": "2020-01-30T23:15:03Z", "tags": ["typographical"]}, {"creationDate": "2020-01-30T12:57:38Z", "tags": ["sonication"]}, {"creationDate": "2020-01-30T05:41:13Z", "tags": ["hobbyhorse"]}, {"creationDate": "2020-01-28T21:15:47Z", "tags": ["pelow"]}, {"creationDate": "2020-01-28T11:36:24Z", "tags": ["pelow"]}, {"creationDate": "2020-01-28T00:43:07Z", "tags": ["pelow"]}, {"creationDate": "2020-01-27T15:31:17Z", "tags": ["pelow"]}, {"creationDate": "2020-01-27T05:19:18Z", "tags": ["tankards"]}, {"creationDate": "2020-01-25T22:10:21Z", "tags": ["Wikisource"]}, {"creationDate": "2020-01-25T12:28:12Z", "tags": ["vituperously"]}, {"creationDate": "2020-01-25T02:20:05Z", "tags": ["tankards"]}, {"creationDate": "2020-01-24T20:23:50Z", "tags": ["vituperously"]}, {"creationDate": "2020-01-24T14:05:48Z", "tags": ["typographical"]}, {"creationDate": "2020-01-23T05:10:25Z", "tags": ["hobbyhorse"]}, {"creationDate": "2020-01-22T19:51:03Z", "tags": ["spencer"]}, {"creationDate": "2020-01-22T11:39:37Z", "tags": ["spencer"]}, {"creationDate": "2020-01-22T03:59:23Z", "tags": ["castigating"]}, {"creationDate": "2020-01-21T21:28:46Z", "tags": ["hobbyhorse"]}, {"creationDate": "2020-01-21T16:17:42Z", "tags": ["typographical"]}, {"creationDate": "2020-01-20T06:41:15Z", "tags": ["castigating"]}, {"creationDate": "2020-01-20T00:35:44Z", "tags": ["hobbyhorse"]}, {"creationDate": "2020-01-19T14:22:30Z", "tags": ["Wikisource"]}, {"creationDate": "2020-01-19T07:34:09Z", "tags": ["tankards"]}, {"creationDate": "2020-01-19T00:54:59Z", "tags": ["vituperously"]}, {"creationDate": "2020-01-18T19:37:18Z", "tags": ["shaka"]}, {"creationDate": "2020-01-17T14:01:15Z", "tags": ["vituperously"]}, {"creationDate": "2020-01-17T04:40:11Z", "tags": ["vituperously"]}, {"creationDate": "2020-01-16T21:35:46Z", "tags": ["shaka"]}, {"creationDate": "2020-01-16T12:50:26Z", "tags": ["pelow"]}, {"creationDate": "2020-01-16T06:50:49Z", "tags": ["shaka"]}, {"creationDate": "2020-01-15T22:59:56Z", "tags": ["spencer"]}, {"creationDate": "2020-01-15T16:11:10Z", "tags": ["pelow"]}, {"creationDate": "2020-01-15T09:23:51Z", "tags": ["vituperously"]}, {"creationDate": "2020-01-14T01:49:15Z", "tags": ["vituperously"]}, {"creationDate": "2020-01-13T19:16:54Z", "tags": ["shaka"]}, {"creationDate": "2020-01-13T11:35:44Z", "tags": ["typographical"]}, {"creationDate": "2020-01-13T03:08:44Z", "tags": ["shaka"]}, {"creationDate": "2020-01-12T18:04:09Z", "tags": ["typographical"]}, {"creationDate": "2020-01-12T12:40:22Z", "tags": ["tankards"]}, {"creationDate": "2020-01-11T07:13:22Z", "tags": ["pelow"]}, {"creationDate": "2020-01-11T01:46:27Z", "tags": ["hobbyhorse"]}, {"creationDate": "2020-01-10T16:07:35Z", "tags": ["vituperously"]}, {"creationDate": "2020-01-10T08:16:24Z", "tags": ["sonication"]}, {"creationDate": "2020-01-09T23:05:14Z", "tags": ["Wikisource"]}, {"creationDate": "2020-01-09T16:10:11Z", "tags": ["typographical"]}, {"creationDate": "2020-01-09T09:15:48Z", "tags": ["hobbyhorse"]}, {"creationDate": "2020-01-08T22:35:45Z", "tags": ["shaka"]}, {"creationDate": "2020-01-08T13:16:56Z", "tags": ["sonication"]}, {"creationDate": "2020-01-07T08:12:24Z", "tags": ["Wikisource"]}, {"creationDate": "2020-01-07T02:34:37Z", "tags": ["Wikisource"]}, {"creationDate": "2020-01-06T16:53:09Z", "tags": ["tankards"]}, {"creationDate": "2020-01-06T06:33:21Z", "tags": ["Wikisource"]}, {"creationDate": "2020-01-06T00:57:20Z", "tags": ["shaka"]}, {"creationDate": "2020-01-05T19:15:45Z", "tags": ["vituperously"]}, {"creationDate": "2020-01-05T12:24:47Z", "tags": ["castigating"]}, {"creationDate": "2020-01-05T03:24:20Z", "tags": ["tankards"]}, {"creationDate": "2020-01-04T20:14:09Z", "tags": ["shaka"]}, {"creationDate": "2020-01-03T11:14:43Z", "tags": ["Wikisource"]}, {"creationDate": "2020-01-03T04:41:03Z", "tags": ["shaka"]}, {"creationDate": "2020-01-02T22:06:10Z", "tags": ["pelow"]}, {"creationDate": "2020-01-02T16:57:40Z", "tags": ["Wikisource"]}, {"creationDate": "2020-01-02T10:17:10Z", "tags": ["Wikisource"]}, {"creationDate": "2020-01-02T04:18:20Z", "tags": ["Wikisource"]}, {"creationDate": "2020-01-01T19:30:23Z", "tags": ["pelow"]}, {"creationDate": "2020-01-01T13:02:13Z", "tags": ["pelow"]}, {"creationDate": "2020-01-01T06:37:28Z", "tags": ["tankards"]}, {"creationDate": "2019-12-30T23:27:36Z", "tags": ["tankards"]}, {"creationDate": "2019-12-30T17:54:58Z", "tags": ["typographical"]}, {"creationDate": "2019-12-30T10:06:55Z", "tags": ["sonication"]}, {"creationDate": "2019-12-30T03:47:55Z", "tags": ["hobbyhorse"]}, {"creationDate": "2019-12-29T17:05:35Z", "tags": ["vituperously"]}, {"creationDate": "2019-12-29T11:10:32Z", "tags": ["shaka"]}, {"creationDate": "2019-12-28T02:08:53Z", "tags": ["Wikisource"]}, {"creationDate": "2019-12-27T18:50:16Z", "tags": ["Wikisource"]}, {"creationDate": "2019-12-27T09:21:31Z", "tags": ["castigating"]}, {"creationDate": "2019-12-27T00:09:40Z", "tags": ["castigating"]}, {"creationDate": "2019-12-26T17:59:24Z", "tags": ["Wikisource"]}, {"creationDate": "2019-12-26T12:25:44Z", "tags": ["vituperously"]}, {"creationDate": "2019-12-26T03:25:26Z", "tags": ["vituperously"]}, {"creationDate": "2019-12-24T21:52:23Z", "tags": ["tankards"]}, {"creationDate": "2019-12-24T13:26:40Z", "tags": ["castigating"]}, {"creationDate": "2019-12-24T05:22:30Z", "tags": ["tankards"]}, {"creationDate": "2019-12-23T20:26:22Z", "tags": ["vituperously"]}, {"creationDate": "2019-12-23T13:46:48Z", "tags": ["hobbyhorse"]}, {"creationDate": "2019-12-23T07:02:07Z", "tags": ["shaka"]}, {"creationDate": "2019-12-21T23:01:32Z", "tags": ["castigating"]}, {"creationDate": "2019-12-21T13:28:56Z", "tags": ["castigating"]}, {"creationDate": "2019-12-21T07:07:34Z", "tags": ["Wikisource"]}, {"creationDate": "2019-12-20T21:06:29Z", "tags": ["vituperously"]}, {"creationDate": "2019-12-20T14:32:53Z", "tags": ["shaka"]}, {"creationDate": "2019-12-20T04:17:40Z", "tags": ["vituperously"]}, {"creationDate": "2019-12-19T20:17:21Z", "tags": ["typographical"]}, {"creationDate": "2019-12-19T11:54:32Z", "tags": ["castigating"]}, {"creationDate": "2019-12-18T02:55:57Z", "tags": ["hobbyhorse"]}, {"creationDate": "2019-12-17T19:17:34Z", "tags": ["pelow"]}, {"creationDate": "2019-12-17T13:53:50Z", "tags": ["castigating"]}, {"creationDate": "2019-12-17T03:06:47Z", "tags": ["pelow"]}, {"creationDate": "2019-12-16T21:24:25Z", "tags": ["shaka"]}, {"creationDate": "2019-12-15T11:25:24Z", "tags": ["hobbyhorse"]}, {"creationDate": "2019-12-15T02:45:54Z", "tags": ["vituperously"]}, {"creationDate": "2019-12-14T17:24:55Z", "tags": ["typographical"]}, {"creationDate": "2019-12-14T09:20:09Z", "tags": ["pelow"]}, {"creationDate": "2019-12-13T22:37:40Z", "tags": ["vituperously"]}, {"creationDate": "2019-12-13T12:42:14Z", "tags": ["shaka"]}, {"creationDate": "2019-12-13T06:48:02Z", "tags": ["pelow"]}, {"creationDate": "2019-12-11T20:37:22Z", "tags": ["tankards"]}, {"creationDate": "2019-12-11T12:16:59Z", "tags": ["vituperously"]}, {"creationDate": "2019-12-11T01:46:45Z", "tags": ["hobbyhorse"]}, {"creationDate": "2019-12-10T20:17:40Z", "tags": ["sonication"]}, {"creationDate": "2019-12-10T15:12:38Z", "tags": ["vituperously"]}, {"creationDate": "2019-12-10T04:37:56Z", "tags": ["tankards"]}, {"creationDate": "2019-12-09T19:11:07Z", "tags": ["pelow"]}, {"creationDate": "2019-12-09T13:17:11Z", "tags": ["typographical"]}, {"creationDate": "2019-12-09T06:30:14Z", "tags": ["hobbyhorse"]}, {"creationDate": "2019-12-08T20:09:53Z", "tags": ["hobbyhorse"]}, {"creationDate": "2019-12-07T12:16:09Z", "tags": ["Wikisource"]}, {"creationDate": "2019-12-07T05:53:56Z", "tags": ["vituperously"]}, {"creationDate": "2019-12-06T23:11:56Z", "tags": ["sonication"]}, {"creationDate": "2019-12-06T16:19:32Z", "tags": ["shaka"]}, {"creationDate": "2019-12-06T07:58:03Z", "tags": ["shaka"]}, {"creationDate": "2019-12-05T01:48:59Z", "tags": ["sonication"]}, {"creationDate": "2019-12-04T19:33:22Z", "tags": ["tankards"]}, {"creationDate": "2019-12-04T09:49:59Z", "tags": ["pelow"]}, {"creationDate": "2019-12-04T04:30:54Z", "tags": ["tankards"]}, {"creationDate": "2019-12-03T22:41:05Z", "tags": ["spencer"]}, {"creationDate": "2019-12-02T13:32:35Z", "tags": ["spencer"]}, {"creationDate": "2019-12-02T07:56:55Z", "tags": ["hobbyhorse"]}, {"creationDate": "2019-12-01T23:20:57Z", "tags": ["castigating"]}, {"creationDate": "2019-12-01T17:41:28Z", "tags": ["pelow"]}, {"creationDate": "2019-12-01T11:45:10Z", "tags": ["vituperously"]}, {"creationDate": "2019-12-01T06:30:19Z", "tags": ["tankards"]}, {"creationDate": "2019-11-29T20:14:50Z", "tags": ["pelow"]}, {"creationDate": "2019-11-29T13:58:51Z", "tags": ["vituperously"]}, {"creationDate": "2019-11-29T05:27:10Z", "tags": ["pelow"]}, {"creationDate": "2019-11-28T18:29:43Z", "tags": ["shaka"]}, {"creationDate": "2019-11-28T09:23:21Z", "tags": ["vituperously"]}, {"creationDate": "2019-11-27T22:23:39Z", "tags": ["shaka"]}, {"creationDate": "2019-11-27T15:52:36Z", "tags": ["castigating"]}, {"creationDate": "2019-11-27T07:22:20Z", "tags": ["castigating"]}, {"creationDate": "2019-11-27T00:08:37Z", "tags": ["Wikisource"]}, {"creationDate": "2019-11-25T17:47:13Z", "tags": ["vituperously"]}, {"creationDate": "2019-11-25T11:13:16Z", "tags": ["typographical"]}, {"creationDate": "2019-11-25T01:49:38Z", "tags": ["pelow"]}, {"creationDate": "2019-11-24T17:56:49Z", "tags": ["tankards"]}, {"creationDate": "2019-11-24T09:33:10Z", "tags": ["typographical"]}, {"creationDate": "2019-11-24T03:56:57Z", "tags": ["typographical"]}, {"creationDate": "2019-11-23T18:37:43Z", "tags": ["tankards"]}, {"creationDate": "2019-11-23T09:12:06Z", "tags": ["hobbyhorse"]}, {"creationDate": "2019-11-22T22:44:33Z", "tags": ["sonication"]}, {"creationDate": "2019-11-21T12:25:56Z", "tags": ["Wikisource"]}, {"creationDate": "2019-11-21T02:19:05Z", "tags": ["sonication"]}, {"creationDate": "2019-11-20T16:50:12Z", "tags": ["typographical"]}, {"creationDate": "2019-11-20T10:29:37Z", "tags": ["sonication"]}, {"creationDate": "2019-11-20T02:47:13Z", "tags": ["castigating"]}, {"creationDate": "2019-11-19T18:57:05Z", "tags": ["Wikisource"]}, {"creationDate": "2019-11-19T10:26:28Z", "tags": ["Wikisource"]}, {"creationDate": "2019-11-18T02:24:03Z", "tags": ["tankards"]}, {"creationDate": "2019-11-17T18:12:40Z", "tags": ["vituperously"]}, {"creationDate": "2019-11-17T08:38:17Z", "tags": ["castigating"]}, {"creationDate": "2019-11-16T22:47:53Z", "tags": ["castigating"]}, {"creationDate": "2019-11-16T12:26:42Z", "tags": ["vituperously"]}, {"creationDate": "2019-11-16T04:25:02Z", "tags": ["spencer"]}, {"creationDate": "2019-11-15T22:08:09Z", "tags": ["sonication"]}, {"creationDate": "2019-11-15T16:23:13Z", "tags": ["Wikisource"]}, {"creationDate": "2019-11-14T06:49:03Z", "tags": ["typographical"]}, {"creationDate": "2019-11-14T01:07:37Z", "tags": ["castigating"]}, {"creationDate": "2019-11-13T16:26:16Z", "tags": ["pelow"]}, {"creationDate": "2019-11-13T06:07:54Z", "tags": ["castigating"]}, {"creationDate": "2019-11-12T20:38:47Z", "tags": ["sonication"]}, {"creationDate": "2019-11-12T12:29:24Z", "tags": ["spencer"]}, {"creationDate": "2019-11-12T05:14:01Z", "tags": ["tankards"]}, {"creationDate": "2019-11-11T19:53:31Z", "tags": ["sonication"]}, {"creationDate": "2019-11-11T11:44:02Z", "tags": ["typographical"]}, {"creationDate": "2019-11-10T02:30:55Z", "tags": ["hobbyhorse"]}, {"creationDate": "2019-11-09T20:18:25Z", "tags": ["shaka"]}, {"creationDate": "2019-11-09T09:53:20Z", "tags": ["tankards"]}, {"creationDate": "2019-11-08T23:11:02Z", "tags": ["sonication"]}, {"creationDate": "2019-11-08T17:29:33Z", "tags": ["pelow"]}, {"creationDate": "2019-11-08T09:25:32Z", "tags": ["Wikisource"]}, {"creationDate": "2019-11-06T22:51:16Z", "tags": ["typographical"]}, {"creationDate": "2019-11-06T13:44:22Z", "tags": ["pelow"]}, {"creationDate": "2019-11-06T03:56:37Z", "tags": ["tankards"]}, {"creationDate": "2019-11-05T19:03:18Z", "tags": ["sonication"]}, {"creationDate": "2019-11-05T08:51:43Z", "tags": ["typographical"]}, {"creationDate": "2019-11-04T02:43:56Z", "tags": ["pelow"]}, {"creationDate": "2019-11-03T17:36:11Z", "tags": ["Wikisource"]}, {"creationDate": "2019-11-03T08:27:33Z", "tags": ["hobbyhorse"]}, {"creationDate": "2019-11-03T00:02:48Z", "tags": ["tankards"]}, {"creationDate": "2019-11-02T15:34:10Z", "tags": ["sonication"]}, {"creationDate": "2019-11-02T06:42:27Z", "tags": ["pelow"]}, {"creationDate": "2019-11-01T22:38:10Z", "tags": ["sonication"]}, {"creationDate": "2019-11-01T13:37:38Z", "tags": ["tankards"]}, {"creationDate": "2019-10-31T03:15:39Z", "tags": ["Wikisource"]}, {"creationDate": "2019-10-30T16:23:08Z", "tags": ["typographical"]}, {"creationDate": "2019-10-30T08:23:53Z", "tags": ["tankards"]}, {"creationDate": "2019-10-30T03:12:26Z", "tags": ["spencer"]}, {"creationDate": "2019-10-29T18:57:58Z", "tags": ["vituperously"]}, {"creationDate": "2019-10-29T12:38:56Z", "tags": ["shaka"]}, {"creationDate": "2019-10-29T07:33:51Z", "tags": ["typographical"]}, {"creationDate": "2019-10-29T01:36:24Z", "tags": ["tankards"]}, {"creationDate": "2019-10-27T19:50:13Z", "tags": ["typographical"]}, {"creationDate": "2019-10-27T09:12:54Z", "tags": ["castigating"]}, {"creationDate": "2019-10-27T03:25:42Z", "tags": ["Wikisource"]}, {"creationDate": "2019-10-26T18:42:35Z", "tags": ["shaka"]}, {"creationDate": "2019-10-26T11:28:32Z", "tags": ["sonication"]}, {"creationDate": "2019-10-26T05:04:10Z", "tags": ["vituperously"]}, {"creationDate": "2019-10-25T19:07:42Z", "tags": ["spencer"]}, {"creationDate": "2019-10-25T12:49:30Z", "tags": ["tankards"]}, {"creationDate": "2019-10-25T05:11:43Z", "tags": ["spencer"]}, {"creationDate": "2019-10-24T19:40:58Z", "tags": ["shaka"]}, {"creationDate": "2019-10-23T10:46:21Z", "tags": ["spencer"]}, {"creationDate": "2019-10-23T00:23:25Z", "tags": ["spencer"]}, {"creationDate": "2019-10-22T18:27:50Z", "tags": ["spencer"]}, {"creationDate": "2019-10-22T08:12:48Z", "tags": ["typographical"]}, {"creationDate": "2019-10-21T22:20:08Z", "tags": ["vituperously"]}, {"creationDate": "2019-10-21T17:18:43Z", "tags": ["shaka"]}, {"creationDate": "2019-10-21T09:43:35Z", "tags": ["castigating"]}, {"creationDate": "2019-10-21T00:27:45Z", "tags": ["pelow"]}, {"creationDate": "2019-10-20T18:33:49Z", "tags": ["spencer"]}, {"creationDate": "2019-10-20T08:31:48Z", "tags": ["castigating"]}, {"creationDate": "2019-10-19T02:45:17Z", "tags": ["hobbyhorse"]}, {"creationDate": "2019-10-18T21:35:34Z", "tags": ["pelow"]}, {"creationDate": "2019-10-18T16:19:01Z", "tags": ["vituperously"]}, {"creationDate": "2019-10-18T08:25:53Z", "tags": ["Wikisource"]}, {"creationDate": "2019-10-18T01:07:26Z", "tags": ["vituperously"]}, {"creationDate": "2019-10-17T15:17:26Z", "tags": ["castigating"]}, {"creationDate": "2019-10-16T07:00:05Z", "tags": ["pelow"]}, {"creationDate": "2019-10-15T21:03:15Z", "tags": ["vituperously"]}, {"creationDate": "2019-10-15T15:15:08Z", "tags": ["tankards"]}, {"creationDate": "2019-10-15T07:14:50Z", "tags": ["Wikisource"]}, {"creationDate": "2019-10-14T22:23:58Z", "tags": ["hobbyhorse"]}, {"creationDate": "2019-10-14T12:25:55Z", "tags": ["pelow"]}, {"creationDate": "2019-10-14T02:16:39Z", "tags": ["castigating"]}, {"creationDate": "2019-10-13T21:01:41Z", "tags": ["hobbyhorse"]}, {"creationDate": "2019-10-13T14:47:05Z", "tags": ["tankards"]}, {"creationDate": "2019-10-13T07:01:21Z", "tags": ["tankards"]}, {"creationDate": "2019-10-11T21:21:54Z", "tags": ["castigating"]}, {"creationDate": "2019-10-11T12:03:55Z", "tags": ["hobbyhorse"]}, {"creationDate": "2019-10-11T06:54:20Z", "tags": ["vituperously"]}, {"creationDate": "2019-10-10T20:29:48Z", "tags": ["shaka"]}, {"creationDate": "2019-10-10T09:31:03Z", "tags": ["vituperously"]}, {"creationDate": "2019-10-08T22:56:09Z", "tags": ["castigating"]}, {"creationDate": "2019-10-08T12:46:44Z", "tags": ["shaka"]}, {"creationDate": "2019-10-08T05:44:54Z", "tags": ["Wikisource"]}, {"creationDate": "2019-10-07T18:48:46Z", "tags": ["hobbyhorse"]}, {"creationDate": "2019-10-07T09:53:06Z", "tags": ["tankards"]}, {"creationDate": "2019-10-07T00:21:34Z", "tags": ["vituperously"]}, {"creationDate": "2019-10-05T17:15:32Z", "tags": ["shaka"]}, {"creationDate": "2019-10-05T08:25:42Z", "tags": ["vituperously"]}, {"creationDate": "2019-10-05T02:43:19Z", "tags": ["tankards"]}, {"creationDate": "2019-10-04T17:52:58Z", "tags": ["hobbyhorse"]}, {"creationDate": "2019-10-04T10:25:29Z", "tags": ["vituperously"]}, {"creationDate": "2019-10-04T01:41:45Z", "tags": ["sonication"]}, {"creationDate": "2019-10-03T15:05:31Z", "tags": ["spencer"]}, {"creationDate": "2019-10-03T07:16:58Z", "tags": ["castigating"]}, {"creationDate": "2019-10-02T00:12:59Z", "tags": ["tankards"]}, {"creationDate": "2019-10-01T16:11:06Z", "tags": ["pelow"]}, {"creationDate": "2019-10-01T09:40:55Z", "tags": ["hobbyhorse"]}, {"creationDate": "2019-09-30T23:23:08Z", "tags": ["spencer"]}, {"creationDate": "2019-09-30T15:55:53Z", "tags": ["spencer"]}, {"creationDate": "2019-09-30T07:44:57Z", "tags": ["shaka"]}, {"creationDate": "2019-09-30T01:14:00Z", "tags": ["typographical"]}, {"creationDate": "2019-09-29T15:54:16Z", "tags": ["vituperously"]}, {"creationDate": "2019-09-29T08:03:11Z", "tags": ["Wikisource"]}, {"creationDate": "2019-09-28T22:42:34Z", "tags": ["sonication"]}, {"creationDate": "2019-09-27T14:16:33Z", "tags": ["hobbyhorse"]}, {"creationDate": "2019-09-27T09:04:53Z", "tags": ["tankards"]}, {"creationDate": "2019-09-27T03:57:00Z", "tags": ["spencer"]}, {"creationDate": "2019-09-26T20:54:25Z", "tags": ["castigating"]}, {"creationDate": "2019-09-26T15:27:38Z", "tags": ["shaka"]}, {"creationDate": "2019-09-26T04:41:05Z", "tags": ["typographical"]}, {"creationDate": "2019-09-25T22:48:35Z", "tags": ["hobbyhorse"]}, {"creationDate": "2019-09-25T15:10:35Z", "tags": ["shaka"]}, {"creationDate": "2019-09-25T04:58:45Z", "tags": ["hobbyhorse"]}, {"creationDate": "2019-09-23T19:44:20Z", "tags": ["hobbyhorse"]}, {"creationDate": "2019-09-23T10:50:45Z", "tags": ["sonication"]}, {"creationDate": "2019-09-23T01:20:59Z", "tags": ["sonication"]}, {"creationDate": "2019-09-22T17:40:50Z", "tags": ["castigating"]}, {"creationDate": "2019-09-22T06:42:22Z", "tags": ["castigating"]}, {"creationDate": "2019-09-21T23:26:54Z", "tags": ["tankards"]}, {"creationDate": "2019-09-21T12:39:29Z", "tags": ["castigating"]}, {"creationDate": "2019-09-21T03:22:26Z", "tags": ["tankards"]}, {"creationDate": "2019-09-19T19:44:26Z", "tags": ["Wikisource"]}, {"creationDate": "2019-09-19T09:42:22Z", "tags": ["shaka"]}, {"creationDate": "2019-09-18T23:16:57Z", "tags": ["shaka"]}, {"creationDate": "2019-09-18T13:06:59Z", "tags": ["typographical"]}, {"creationDate": "2019-09-18T04:20:36Z", "tags": ["castigating"]}, {"creationDate": "2019-09-17T18:34:58Z", "tags": ["castigating"]}, {"creationDate": "2019-09-17T13:14:52Z", "tags": ["Wikisource"]}, {"creationDate": "2019-09-17T08:13:35Z", "tags": ["pelow"]}, {"creationDate": "2019-09-17T00:17:21Z", "tags": ["shaka"]}, {"creationDate": "2019-09-15T19:02:18Z", "tags": ["tankards"]}, {"creationDate": "2019-09-15T10:13:33Z", "tags": ["tankards"]}, {"creationDate": "2019-09-15T01:59:50Z", "tags": ["shaka"]}, {"creationDate": "2019-09-14T18:59:15Z", "tags": ["pelow"]}, {"creationDate": "2019-09-14T11:01:07Z", "tags": ["shaka"]}, {"creationDate": "2019-09-14T00:14:01Z", "tags": ["tankards"]}, {"creationDate": "2019-09-13T16:31:42Z", "tags": ["shaka"]}, {"creationDate": "2019-09-13T09:13:50Z", "tags": ["Wikisource"]}, {"creationDate": "2019-09-13T02:58:49Z", "tags": ["spencer"]}, {"creationDate": "2019-09-12T17:24:18Z", "tags": ["shaka"]}, {"creationDate": "2019-09-11T07:58:43Z", "tags": ["vituperously"]}, {"creationDate": "2019-09-10T20:58:23Z", "tags": ["pelow"]}, {"creationDate": "2019-09-10T12:29:25Z", "tags": ["vituperously"]}, {"creationDate": "2019-09-10T04:33:31Z", "tags": ["Wikisource"]}, {"creationDate": "2019-09-09T21:42:00Z", "tags": ["shaka"]}, {"creationDate": "2019-09-09T13:52:54Z", "tags": ["shaka"]}, {"creationDate": "2019-09-08T06:16:38Z", "tags": ["shaka"]}, {"creationDate": "2019-09-07T19:20:18Z", "tags": ["Wikisource"]}, {"creationDate": "2019-09-07T11:39:18Z", "tags": ["tankards"]}, {"creationDate": "2019-09-07T04:17:19Z", "tags": ["spencer"]}, {"creationDate": "2019-09-06T18:22:16Z", "tags": ["castigating"]}, {"creationDate": "2019-09-06T10:51:54Z", "tags": ["sonication"]}, {"creationDate": "2019-09-06T04:37:08Z", "tags": ["vituperously"]}, {"creationDate": "2019-09-05T23:13:21Z", "tags": ["typographical"]}, {"creationDate": "2019-09-05T15:06:13Z", "tags": ["Wikisource"]}, {"creationDate": "2019-09-05T05:43:02Z", "tags": ["hobbyhorse"]}, {"creationDate": "2019-09-03T23:49:11Z", "tags": ["hobbyhorse"]}, {"creationDate": "2019-09-03T12:48:54Z", "tags": ["shaka"]}, {"creationDate": "2019-09-03T06:31:28Z", "tags": ["pelow"]}, {"creationDate": "2019-09-02T20:55:58Z", "tags": ["vituperously"]}, {"creationDate": "2019-09-02T14:25:23Z", "tags": ["hobbyhorse"]}, {"creationDate": "2019-09-01T04:12:49Z", "tags": ["shaka"]}, {"creationDate": "2019-08-31T19:27:55Z", "tags": ["castigating"]}, {"creationDate": "2019-08-31T13:27:21Z", "tags": ["castigating"]}, {"creationDate": "2019-08-31T03:07:17Z", "tags": ["vituperously"]}, {"creationDate": "2019-08-30T16:57:11Z", "tags": ["Wikisource"]}, {"creationDate": "2019-08-30T07:59:20Z", "tags": ["typographical"]}, {"creationDate": "2019-08-30T00:06:50Z", "tags": ["Wikisource"]}, {"creationDate": "2019-08-29T17:55:59Z", "tags": ["castigating"]}, {"creationDate": "2019-08-29T06:57:09Z", "tags": ["typographical"]}, {"creationDate": "2019-08-27T23:01:50Z", "tags": ["Wikisource"]}, {"creationDate": "2019-08-27T17:00:08Z", "tags": ["pelow"]}, {"creationDate": "2019-08-27T09:10:07Z", "tags": ["shaka"]}, {"creationDate": "2019-08-27T00:06:26Z", "tags": ["hobbyhorse"]}, {"creationDate": "2019-08-26T15:46:48Z", "tags": ["typographical"]}, {"creationDate": "2019-08-26T06:05:32Z", "tags": ["shaka"]}, {"creationDate": "2019-08-24T20:01:07Z", "tags": ["typographical"]}, {"creationDate": "2019-08-24T11:45:02Z", "tags": ["vituperously"]}, {"creationDate": "2019-08-24T01:50:00Z", "tags": ["typographical"]}, {"creationDate": "2019-08-23T17:54:54Z", "tags": ["tankards"]}, {"creationDate": "2019-08-23T08:47:59Z", "tags": ["castigating"]}, {"creationDate": "2019-08-23T01:17:10Z", "tags": ["pelow"]}, {"creationDate": "2019-08-22T15:31:41Z", "tags": ["tankards"]}, {"creationDate": "2019-08-21T06:59:21Z", "tags": ["typographical"]}, {"creationDate": "2019-08-20T22:34:54Z", "tags": ["spencer"]}, {"creationDate": "2019-08-20T17:32:56Z", "tags": ["vituperously"]}, {"creationDate": "2019-08-20T09:31:07Z", "tags": ["pelow"]}, {"creationDate": "2019-08-19T23:56:08Z", "tags": ["tankards"]}, {"creationDate": "2019-08-19T17:13:12Z", "tags": ["spencer"]}, {"creationDate": "2019-08-18T08:35:02Z", "tags": ["vituperously"]}, {"creationDate": "2019-08-18T02:46:54Z", "tags": ["sonication"]}, {"creationDate": "2019-08-17T19:49:28Z", "tags": ["castigating"]}, {"creationDate": "2019-08-17T13:06:52Z", "tags": ["sonication"]}, {"creationDate": "2019-08-17T02:36:06Z", "tags": ["tankards"]}, {"creationDate": "2019-08-16T17:00:35Z", "tags": ["pelow"]}, {"creationDate": "2019-08-15T07:42:41Z", "tags": ["tankards"]}, {"creationDate": "2019-08-15T01:25:12Z", "tags": ["shaka"]}, {"creationDate": "2019-08-14T15:48:48Z", "tags": ["tankards"]}, {"creationDate": "2019-08-14T07:37:45Z", "tags": ["castigating"]}, {"creationDate": "2019-08-13T23:26:27Z", "tags": ["shaka"]}, {"creationDate": "2019-08-13T13:51:45Z", "tags": ["pelow"]}, {"creationDate": "2019-08-12T05:38:18Z", "tags": ["shaka"]}, {"creationDate": "2019-08-11T23:32:09Z", "tags": ["shaka"]}, {"creationDate": "2019-08-11T18:27:28Z", "tags": ["typographical"]}, {"creationDate": "2019-08-11T09:43:09Z", "tags": ["sonication"]}, {"creationDate": "2019-08-10T22:58:00Z", "tags": ["spencer"]}, {"creationDate": "2019-08-10T17:32:56Z", "tags": ["spencer"]}, {"creationDate": "2019-08-10T11:42:06Z", "tags": ["Wikisource"]}, {"creationDate": "2019-08-10T02:59:54Z", "tags": ["Wikisource"]}, {"creationDate": "2019-08-09T16:07:48Z", "tags": ["pelow"]}, {"creationDate": "2019-08-08T08:31:50Z", "tags": ["spencer"]}, {"creationDate": "2019-08-07T23:11:41Z", "tags": ["shaka"]}, {"creationDate": "2019-08-07T12:12:19Z", "tags": ["tankards"]}, {"creationDate": "2019-08-07T04:59:20Z", "tags": ["shaka"]}, {"creationDate": "2019-08-06T20:42:43Z", "tags": ["Wikisource"]}, {"creationDate": "2019-08-05T13:38:34Z", "tags": ["spencer"]}, {"creationDate": "2019-08-05T07:21:22Z", "tags": ["castigating"]}, {"creationDate": "2019-08-04T21:11:02Z", "tags": ["sonication"]}, {"creationDate": "2019-08-04T12:13:31Z", "tags": ["tankards"]}, {"creationDate": "2019-08-04T01:37:26Z", "tags": ["tankards"]}, {"creationDate": "2019-08-03T16:35:56Z", "tags": ["sonication"]}, {"creationDate": "2019-08-03T07:36:19Z", "tags": ["castigating"]}, {"creationDate": "2019-08-02T22:47:16Z", "tags": ["hobbyhorse"]}, {"creationDate": "2019-08-01T13:17:55Z", "tags": ["hobbyhorse"]}, {"creationDate": "2019-08-01T05:57:25Z", "tags": ["pelow"]}, {"creationDate": "2019-07-31T23:39:35Z", "tags": ["shaka"]}, {"creationDate": "2019-07-31T13:33:09Z", "tags": ["tankards"]}, {"creationDate": "2019-07-31T05:46:02Z", "tags": ["tankards"]}, {"creationDate": "2019-07-29T20:24:42Z", "tags": ["tankards"]}, {"creationDate": "2019-07-29T09:51:46Z", "tags": ["spencer"]}, {"creationDate": "2019-07-29T03:50:54Z", "tags": ["spencer"]}, {"creationDate": "2019-07-28T20:24:30Z", "tags": ["shaka"]}, {"creationDate": "2019-07-28T11:42:21Z", "tags": ["typographical"]}, {"creationDate": "2019-07-28T03:10:09Z", "tags": ["castigating"]}, {"creationDate": "2019-07-26T20:47:29Z", "tags": ["typographical"]}, {"creationDate": "2019-07-26T14:03:05Z", "tags": ["tankards"]}, {"creationDate": "2019-07-26T06:35:33Z", "tags": ["vituperously"]}, {"creationDate": "2019-07-26T01:00:05Z", "tags": ["castigating"]}, {"creationDate": "2019-07-25T18:53:05Z", "tags": ["shaka"]}, {"creationDate": "2019-07-25T13:42:28Z", "tags": ["tankards"]}, {"creationDate": "2019-07-25T04:16:19Z", "tags": ["vituperously"]}, {"creationDate": "2019-07-24T22:02:13Z", "tags": ["spencer"]}, {"creationDate": "2019-07-24T14:49:28Z", "tags": ["castigating"]}, {"creationDate": "2019-07-23T05:18:13Z", "tags": ["typographical"]}, {"creationDate": "2019-07-22T23:50:00Z", "tags": ["vituperously"]}, {"creationDate": "2019-07-22T13:10:23Z", "tags": ["spencer"]}, {"creationDate": "2019-07-22T03:25:23Z", "tags": ["sonication"]}, {"creationDate": "2019-07-21T19:23:42Z", "tags": ["Wikisource"]}, {"creationDate": "2019-07-21T11:31:33Z", "tags": ["pelow"]}, {"creationDate": "2019-07-21T01:10:33Z", "tags": ["hobbyhorse"]}, {"creationDate": "2019-07-19T15:54:36Z", "tags": ["tankards"]}, {"creationDate": "2019-07-19T10:47:15Z", "tags": ["tankards"]}, {"creationDate": "2019-07-19T03:12:27Z", "tags": ["hobbyhorse"]}, {"creationDate": "2019-07-18T18:47:37Z", "tags": ["sonication"]}, {"creationDate": "2019-07-18T08:00:15Z", "tags": ["tankards"]}, {"creationDate": "2019-07-18T01:21:15Z", "tags": ["tankards"]}, {"creationDate": "2019-07-17T19:30:48Z", "tags": ["hobbyhorse"]}, {"creationDate": "2019-07-16T12:20:06Z", "tags": ["tankards"]}, {"creationDate": "2019-07-16T03:19:35Z", "tags": ["Wikisource"]}, {"creationDate": "2019-07-15T19:01:46Z", "tags": ["tankards"]}, {"creationDate": "2019-07-15T11:37:56Z", "tags": ["typographical"]}, {"creationDate": "2019-07-15T02:32:26Z", "tags": ["pelow"]}, {"creationDate": "2019-07-14T20:37:56Z", "tags": ["castigating"]}, {"creationDate": "2019-07-14T14:10:07Z", "tags": ["shaka"]}, {"creationDate": "2019-07-13T08:30:20Z", "tags": ["sonication"]}, {"creationDate": "2019-07-13T00:09:38Z", "tags": ["Wikisource"]}, {"creationDate": "2019-07-12T18:39:56Z", "tags": ["tankards"]}, {"creationDate": "2019-07-12T08:47:33Z", "tags": ["hobbyhorse"]}, {"creationDate": "2019-07-11T22:28:43Z", "tags": ["pelow"]}, {"creationDate": "2019-07-11T16:01:00Z", "tags": ["spencer"]}, {"creationDate": "2019-07-11T09:48:00Z", "tags": ["shaka"]}, {"creationDate": "2019-07-10T23:51:55Z", "tags": ["typographical"]}, {"creationDate": "2019-07-10T14:19:23Z", "tags": ["shaka"]}, {"creationDate": "2019-07-10T06:15:31Z", "tags": ["shaka"]}]}